LogiTyme/__init__.py
LogiTyme/logityme.py
LogiTyme-0.0.9.dist-info/LICENSE
LogiTyme-0.0.9.dist-info/METADATA
LogiTyme-0.0.9.dist-info/WHEEL
LogiTyme-0.0.9.dist-info/top_level.txt
LogiTyme-0.0.9.dist-info/RECORD
