Metadata-Version: 2.1
Name: LogiTyme
Version: 0.0.9
Summary: LogiTyme is a Python package used to track the time spent on each function, custom functions, and the entire Python Program.
Home-page: https://github.com/lmas3009/LogiTyme
Author: Aravind Kumar Vemula
Author-email: 30lmas09@gmail.com
Keywords: logging,analyzing
Classifier: Intended Audience :: Developers
Classifier: Programming Language :: Python :: 3
Classifier: Operating System :: Unix
Classifier: Operating System :: MacOS :: MacOS X
Classifier: Operating System :: Microsoft :: Windows
Requires-Python: >=3.8
License-File: LICENSE
Requires-Dist: terminaltables
